middleware/__init__.py
middleware/logging.py
django_logging_requests-1.0.0.dist-info/LICENCE
django_logging_requests-1.0.0.dist-info/METADATA
django_logging_requests-1.0.0.dist-info/WHEEL
django_logging_requests-1.0.0.dist-info/top_level.txt
django_logging_requests-1.0.0.dist-info/RECORD
