Metadata-Version: 2.1
Name: django_logging_requests
Version: 1.0.0
Summary: A package for logging all requests
Author: J4CK_VVH173
Author-email: i78901234567890@gmail.com
Classifier: Programming Language :: Python :: 3
Classifier: License :: OSI Approved :: MIT License
Classifier: Operating System :: OS Independent
Requires-Python: >=3.8
License-File: LICENCE
